pcalg_py/__init__.py
pcalg_py/graph_utils.py
pcalg_py/indep_test.py
pcalg_py/pc.py
pcalg_py/utils.py
pcalg_py-0.0.1.dist-info/licenses/LICENSE
pcalg_py-0.0.1.dist-info/METADATA
pcalg_py-0.0.1.dist-info/WHEEL
pcalg_py-0.0.1.dist-info/top_level.txt
pcalg_py-0.0.1.dist-info/RECORD
