Metadata-Version: 2.4
Name: pcalg-py
Version: 0.0.1
Summary: A Python implementation of the PC algorithm for causal structure learning, ported from the R pcalg package.
Author-email: Eichi Uehara <your.email@example.com>
Project-URL: Homepage, https://github.com/yourusername/pcalg-py
Project-URL: Bug Tracker, https://github.com/yourusername/pcalg-py/issues
Classifier: Programming Language :: Python :: 3
Classifier: License :: OSI Approved :: GNU General Public License v2 (GPLv2)
Classifier: Operating System :: OS Independent
Requires-Python: >=3.8
License-File: LICENSE
Requires-Dist: numpy
Requires-Dist: pandas
Requires-Dist: scipy
Requires-Dist: networkx
Dynamic: license-file
